README.md
setup.py
monnify/__init__.py
monnify/base/__init__.py
monnify/collection/__init__.py
monnify/collection/invoice.py
monnify/collection/reserved_account.py
monnify/collection/transaction.py
monnify/disbursement/__init__.py
monnify/disbursement/bulk_disbursement.py
monnify/disbursement/paycode.py
monnify/disbursement/single_disbursement.py
monnify/exceptions/__init__.py
monnify/settlement/__init__.py
monnify/settlement/sub_account.py
monnify/tests/__init__.py
monnify/tests/test_collections.py
monnify/tests/test_disbursements.py
monnify/tests/test_settlement.py
monnify/tests/test_verifications.py
monnify/validators/__init__.py
monnify/validators/disbursement_validator.py
monnify/validators/invoice_validator.py
monnify/validators/paycode_validator.py
monnify/validators/reserved_account_validator.py
monnify/validators/settlement_validator.py
monnify/validators/transaction_validator.py
monnify/validators/verification_validator.py
monnify/verification/__init__.py
monnify/verification/kyc_verification.py
monnify_python.egg-info/PKG-INFO
monnify_python.egg-info/SOURCES.txt
monnify_python.egg-info/dependency_links.txt
monnify_python.egg-info/requires.txt
monnify_python.egg-info/top_level.txt