Metadata-Version: 2.1
Name: monnify-python
Version: 1.0.0
Summary: Python library for the Monnify API
Home-page: https://github.com/Monnify/pymonnify
Author: Marvelous-Benji
Author-email: integration-support@monnify.com
License: MIT
Platform: UNKNOWN
Classifier: Programming Language :: Python :: 3.6
Classifier: Programming Language :: Python :: 3.7
Classifier: Programming Language :: Python :: 3.8
Classifier: Programming Language :: Python :: 3.9
Classifier: Programming Language :: Python :: 3.10
Classifier: License :: OSI Approved :: MIT License
Classifier: Operating System :: OS Independent
Requires-Python: >=3.6
